quranreader/__init__.py
quranreader/config.py
quranreader/handle_exception.py
quranreader/interface.py
quranreader/parser_quranreader.py
quranreader/quranreader.py
quranreader/service.py
quranreader/utils.py
quranreader-1.0.0.dist-info/METADATA
quranreader-1.0.0.dist-info/WHEEL
quranreader-1.0.0.dist-info/top_level.txt
quranreader-1.0.0.dist-info/RECORD
