Metadata-Version: 2.2
Name: quranreader
Version: 1.0.0
Summary: QuranReader: Package pour gérer les sourates et le coran
Home-page: https://gitlab.com/misternobody01/package_muslimdeen.git
Author: personne monsieur
Author-email: monsieurnobody01@gmail.com
Classifier: Programming Language :: Python :: 3
Classifier: License :: OSI Approved :: MIT License
Classifier: Operating System :: OS Independent
Requires-Python: >=3.6
Requires-Dist: requests==2.32.3
Dynamic: author
Dynamic: author-email
Dynamic: classifier
Dynamic: description
Dynamic: description-content-type
Dynamic: home-page
Dynamic: requires-dist
Dynamic: requires-python
Dynamic: summary
